ndev_themes/__init__.py
ndev_themes/_version.py
ndev_themes/napari.yaml
ndev_themes/_tests/__init__.py
ndev_themes-0.1.0.dist-info/licenses/LICENSE
ndev_themes-0.1.0.dist-info/METADATA
ndev_themes-0.1.0.dist-info/WHEEL
ndev_themes-0.1.0.dist-info/entry_points.txt
ndev_themes-0.1.0.dist-info/top_level.txt
ndev_themes-0.1.0.dist-info/RECORD
