Metadata-Version: 2.4
Name: ndev-themes
Version: 0.1.0
Summary: napari themes for the ndev-kit, for fun
Author: Tim Monko
Author-email: timmonko@gmail.com
License: 
Project-URL: Bug Tracker, https://github.com/ndev-kit/ndev-themes/issues
Project-URL: Documentation, https://github.com/ndev-kit/ndev-themes#README.md
Project-URL: Source Code, https://github.com/ndev-kit/ndev-themes
Project-URL: User Support, https://github.com/ndev-kit/ndev-themes/issues
Classifier: Development Status :: 2 - Pre-Alpha
Classifier: Framework :: napari
Classifier: Intended Audience :: Developers
Classifier: License :: OSI Approved :: BSD License
Classifier: Operating System :: OS Independent
Classifier: Programming Language :: Python
Classifier: Programming Language :: Python :: 3
Classifier: Programming Language :: Python :: 3 :: Only
Classifier: Programming Language :: Python :: 3.10
Classifier: Programming Language :: Python :: 3.11
Classifier: Programming Language :: Python :: 3.12
Classifier: Programming Language :: Python :: 3.13
Classifier: Topic :: Scientific/Engineering :: Image Processing
Requires-Python: >=3.10
License-File: LICENSE
Requires-Dist: numpy
Provides-Extra: all
Requires-Dist: napari[all]; extra == "all"
Provides-Extra: testing
Requires-Dist: tox; extra == "testing"
Requires-Dist: pytest; extra == "testing"
Requires-Dist: pytest-cov; extra == "testing"
Dynamic: license-file
